{
  "sara": [
    "Ogni giornata è un canvas, non una gabbia.",
    "Le idee migliori arrivano quando smetti di forzarle.",
    "Non devi avere fretta, devi avere direzione."
  ],
  "sofia": [
    "Ogni passo fuori dalla comfort zone è un upgrade.",
    "La curiosità è il superpotere che non scade mai.",
    "Non sei in ritardo, sei sul tuo percorso."
  ],
  "simone": [
    "La calma è una tecnologia sottovalutata.",
    "Pensare prima di agire è già un superpotere.",
    "Non devi parlare forte, ti basta essere chiaro."
  ],
  "samuele": [
    "Ogni bug è un rituale che chiede di essere compreso.",
    "Il caos è solo ordine visto troppo da vicino.",
    "I tuoi sistemi non sono strani: sono la tua lingua."
  ],
  "pesca": [
    "Ogni passo è un’avventura.",
    "La felicità è una passeggiata con chi ami.",
    "Annusa il mondo, un momento alla volta.",
    "Per i cani il tempo è semplice: adesso, insieme."
  ]
}
